<xml xmlns="http://www.w3.org/1999/xhtml"><block type="controls_repeat_ext" id="O_j25wxziR?r]gHc^e{F" x="352" y="181"><value name="TIMES"><shadow type="math_number" id=",hpUPKLeqoHGlPZ{NyYM"><field name="NUM">5</field></shadow></value><statement name="DO"><block type="motion_robotvelocity" id="{o[dfv3rI{Pv!/X$i;0("><field name="vx">0</field><field name="vy">0</field><field name="vphi">0.5</field><field name="time">2</field><next><block type="motion_robotvelocity" id="^pzt_X=sQP.C$UKv;mh]"><field name="vx">0</field><field name="vy">0</field><field name="vphi">0</field><field name="time">0.5</field><next><block type="motion_robotvelocity" id="uQSv(uKf2$XVUI^xa%Wv"><field name="vx">0</field><field name="vy">0</field><field name="vphi">-0.5</field><field name="time">2</field><next><block type="motion_robotvelocity" id="eye2a;S_6q||-?uaxH27"><field name="vx">0</field><field name="vy">0</field><field name="vphi">0</field><field name="time">0.5</field></block></next></block></next></block></next></block></statement></block></xml>